hello_world/__init__.py
hello_world/command_line.py
oneccl_binding_pt-0.0.4.dist-info/LICENSE
oneccl_binding_pt-0.0.4.dist-info/METADATA
oneccl_binding_pt-0.0.4.dist-info/WHEEL
oneccl_binding_pt-0.0.4.dist-info/entry_points.txt
oneccl_binding_pt-0.0.4.dist-info/top_level.txt
oneccl_binding_pt-0.0.4.dist-info/RECORD
