Metadata-Version: 2.1
Name: oneccl-binding-pt
Version: 0.0.4
Summary: Intel® oneCCL Bindings for PyTorch (formerly known as torch_ccl)
Home-page: https://github.com/intel/torch-ccl
Author: IntelAI
Author-email: IntelAI@intel.com
License: MIT
Keywords: simplest hello world pypi package
Classifier: Development Status :: 3 - Alpha
Classifier: License :: OSI Approved :: MIT License
Classifier: Programming Language :: Python :: 3.5
Classifier: Programming Language :: Python :: 3.6
Classifier: Programming Language :: Python :: 3.7
Classifier: Programming Language :: Python :: 3.8
Classifier: Topic :: Text Processing :: Linguistic
License-File: LICENSE
